rapidocr/__init__.py
rapidocr/server.py
rapidocr_mcp_server-0.1.7.dist-info/licenses/LICENSE.txt
rapidocr_mcp_server-0.1.7.dist-info/METADATA
rapidocr_mcp_server-0.1.7.dist-info/WHEEL
rapidocr_mcp_server-0.1.7.dist-info/entry_points.txt
rapidocr_mcp_server-0.1.7.dist-info/top_level.txt
rapidocr_mcp_server-0.1.7.dist-info/RECORD
