Metadata-Version: 2.4
Name: rapidocr-mcp-server
Version: 0.1.7
Summary: RapidOCR MCP Server for OCR processing
Author-email: z4none <z4none@gmail.com>
License-Expression: MIT
Project-URL: Homepage, https://github.com/z4none/rapidocr-mcp
Project-URL: Repository, https://github.com/z4none/rapidocr-mcp.git
Keywords: ocr,rapidocr,mcp
Requires-Python: >=3.13
License-File: LICENSE.txt
Requires-Dist: mcp[cli]>=1.6.0
Requires-Dist: onnxruntime==1.19.2
Requires-Dist: rapidocr>=2.0.4
Requires-Dist: requests>=2.32.3
Dynamic: license-file
